test_lib_luan/__init__.py
test_lib_luan/top_stock.py
test_lib_luan-0.1.8.dist-info/METADATA
test_lib_luan-0.1.8.dist-info/WHEEL
test_lib_luan-0.1.8.dist-info/top_level.txt
test_lib_luan-0.1.8.dist-info/RECORD
