Metadata-Version: 2.4
Name: test-lib-luan
Version: 0.1.8
Summary: Đây là thư viện test
Author: Luan
Author-email: 
Dynamic: author
Dynamic: description
Dynamic: description-content-type
Dynamic: summary
